tchu/__init__.py
tchu/amqp_client.py
tchu/consumer.py
tchu/producer.py
tchu/utils/__init__.py
tchu/utils/json_encoder.py
tchu/utils/retry_decorator.py
tchu/version.py
tchu-0.1.2.dist-info/LICENSE
tchu-0.1.2.dist-info/METADATA
tchu-0.1.2.dist-info/WHEEL
tchu-0.1.2.dist-info/RECORD
