Metadata-Version: 2.3
Name: tchu
Version: 0.1.2
Summary: A simple RabbitMQ/Pika wrapper for publishing and consuming events
License: MIT
Keywords: rabbitmq,pika,amqp,messaging
Author: David Sigley
Author-email: djsigley@gmail.com
Requires-Python: >=3.7,<4.0
Classifier: Development Status :: 3 - Alpha
Classifier: Intended Audience :: Developers
Classifier: License :: OSI Approved :: MIT License
Classifier: Programming Language :: Python :: 3
Classifier: Programming Language :: Python :: 3.7
Classifier: Programming Language :: Python :: 3.8
Classifier: Programming Language :: Python :: 3.9
Classifier: Programming Language :: Python :: 3.10
Classifier: Programming Language :: Python :: 3.11
Classifier: Programming Language :: Python :: 3.12
Classifier: Programming Language :: Python :: 3.13
Requires-Dist: pika (>=1.2.0,<2.0.0)
Project-URL: Documentation, https://github.com/sigularusrex/tchu
Project-URL: Homepage, https://github.com/sigularusrex/tchu
Project-URL: Repository, https://github.com/sigularusrex/tchu
